kapa/__init__.py
kapa/kapa.py
kapa/kindictgene.csv
kapa/kindictpro.csv
kapa/unigenedict.csv
kapa-0.0.1.dist-info/LICENSE
kapa-0.0.1.dist-info/METADATA
kapa-0.0.1.dist-info/WHEEL
kapa-0.0.1.dist-info/top_level.txt
kapa-0.0.1.dist-info/RECORD
