Metadata-Version: 2.1
Name: kapa
Version: 0.0.1
Summary: Kinase Activity Profiling Analysis
Home-page: UNKNOWN
Author: Yao Gong
Author-email: gong0062@umn.edu
License: UNKNOWN
Keywords: python,phosphorylation,kinase,enrichment
Platform: UNKNOWN
Classifier: Programming Language :: Python :: 3
Requires-Python: >=3.6, <4
License-File: LICENSE
Requires-Dist: numpy (>1.16.2)
Requires-Dist: pandas (>0.24.1)
Requires-Dist: statistics
Requires-Dist: scipy (>1.6.1)
